humangemlib/Human-GEM.xml
humangemlib/__init__.py
humangemlib/cleaneddata.tsv
humangemlib/fba.py
humangemlib/gwas_input_schema.txt
humangemlib/main.py
humangemlib-1.0.3.dist-info/METADATA
humangemlib-1.0.3.dist-info/WHEEL
humangemlib-1.0.3.dist-info/licenses/LICENSE
humangemlib-1.0.3.dist-info/RECORD
